<?xml version="1.0" encoding="UTF-8" ?>
<PDBx:datablock  datablockName="G" 
            xmlns:PDBx="http://deposit.pdb.org/pdbML/pdbx.xsd"
            xmlns:xsi="http://www.w3.org/2001/XMLSchema-instance"
            xsi:schemaLocation="http://deposit.pdb.org/pdbML/pdbx.xsd pdbx.xsd">
   <PDBx:chem_compCategory>
      <PDBx:chem_comp id="G">
         <PDBx:name>GUANOSINE-5&apos;-MONOPHOSPHATE</PDBx:name>
         <PDBx:type>RNA linking</PDBx:type>
         <PDBx:pdbx_type>ATOMN</PDBx:pdbx_type>
         <PDBx:formula>C10 H14 N5 O8 P</PDBx:formula>
         <PDBx:pdbx_formal_charge>0</PDBx:pdbx_formal_charge>
         <PDBx:pdbx_initial_date>1999-07-08</PDBx:pdbx_initial_date>
         <PDBx:pdbx_modified_date>2011-06-04</PDBx:pdbx_modified_date>
         <PDBx:pdbx_ambiguous_flag>N</PDBx:pdbx_ambiguous_flag>
         <PDBx:pdbx_release_status>REL</PDBx:pdbx_release_status>
         <PDBx:formula_weight>363.221</PDBx:formula_weight>
         <PDBx:one_letter_code>G</PDBx:one_letter_code>
         <PDBx:three_letter_code>G</PDBx:three_letter_code>
         <PDBx:pdbx_model_coordinates_missing_flag>N</PDBx:pdbx_model_coordinates_missing_flag>
         <PDBx:pdbx_ideal_coordinates_missing_flag>N</PDBx:pdbx_ideal_coordinates_missing_flag>
         <PDBx:pdbx_processing_site>RCSB</PDBx:pdbx_processing_site>
      </PDBx:chem_comp>
   </PDBx:chem_compCategory>
   <PDBx:chem_comp_atomCategory>
      <PDBx:chem_comp_atom comp_id="G" atom_id="OP3">
         <PDBx:alt_atom_id>O3P</PDBx:alt_atom_id>
         <PDBx:type_symbol>O</PDBx:type_symbol>
         <PDBx:charge>0</PDBx:charge>
         <PDBx:pdbx_align>1</PDBx:pdbx_align>
         <PDBx:pdbx_aromatic_flag>N</PDBx:pdbx_aromatic_flag>
         <PDBx:pdbx_leaving_atom_flag>Y</PDBx:pdbx_leaving_atom_flag>
         <PDBx:pdbx_stereo_config>N</PDBx:pdbx_stereo_config>
         <PDBx:model_Cartn_x>34.313</PDBx:model_Cartn_x>
         <PDBx:model_Cartn_y>3.314</PDBx:model_Cartn_y>
         <PDBx:model_Cartn_z>-0.422</PDBx:model_Cartn_z>
         <PDBx:pdbx_model_Cartn_x_ideal>-1.945</PDBx:pdbx_model_Cartn_x_ideal>
         <PDBx:pdbx_model_Cartn_y_ideal>-1.360</PDBx:pdbx_model_Cartn_y_ideal>
         <PDBx:pdbx_model_Cartn_z_ideal>5.599</PDBx:pdbx_model_Cartn_z_ideal>
         <PDBx:pdbx_component_atom_id>OP3</PDBx:pdbx_component_atom_id>
         <PDBx:pdbx_component_comp_id>G</PDBx:pdbx_component_comp_id>
         <PDBx:pdbx_ordinal>1</PDBx:pdbx_ordinal>
      </PDBx:chem_comp_atom>
      <PDBx:chem_comp_atom comp_id="G" atom_id="P">
         <PDBx:alt_atom_id>P</PDBx:alt_atom_id>
         <PDBx:type_symbol>P</PDBx:type_symbol>
         <PDBx:charge>0</PDBx:charge>
         <PDBx:pdbx_align>1</PDBx:pdbx_align>
         <PDBx:pdbx_aromatic_flag>N</PDBx:pdbx_aromatic_flag>
         <PDBx:pdbx_leaving_atom_flag>N</PDBx:pdbx_leaving_atom_flag>
         <PDBx:pdbx_stereo_config>N</PDBx:pdbx_stereo_config>
         <PDBx:model_Cartn_x>33.741</PDBx:model_Cartn_x>
         <PDBx:model_Cartn_y>4.431</PDBx:model_Cartn_y>
         <PDBx:model_Cartn_z>0.367</PDBx:model_Cartn_z>
         <PDBx:pdbx_model_Cartn_x_ideal>-0.911</PDBx:pdbx_model_Cartn_x_ideal>
         <PDBx:pdbx_model_Cartn_y_ideal>-0.277</PDBx:pdbx_model_Cartn_y_ideal>
         <PDBx:pdbx_model_Cartn_z_ideal>5.008</PDBx:pdbx_model_Cartn_z_ideal>
         <PDBx:pdbx_component_atom_id>P</PDBx:pdbx_component_atom_id>
         <PDBx:pdbx_component_comp_id>G</PDBx:pdbx_component_comp_id>
         <PDBx:pdbx_ordinal>2</PDBx:pdbx_ordinal>
      </PDBx:chem_comp_atom>
      <PDBx:chem_comp_atom comp_id="G" atom_id="OP1">
         <PDBx:alt_atom_id>O1P</PDBx:alt_atom_id>
         <PDBx:type_symbol>O</PDBx:type_symbol>
         <PDBx:charge>0</PDBx:charge>
         <PDBx:pdbx_align>1</PDBx:pdbx_align>
         <PDBx:pdbx_aromatic_flag>N</PDBx:pdbx_aromatic_flag>
         <PDBx:pdbx_leaving_atom_flag>N</PDBx:pdbx_leaving_atom_flag>
         <PDBx:pdbx_stereo_config>N</PDBx:pdbx_stereo_config>
         <PDBx:model_Cartn_x>33.537</PDBx:model_Cartn_x>
         <PDBx:model_Cartn_y>5.671</PDBx:model_Cartn_y>
         <PDBx:model_Cartn_z>-0.451</PDBx:model_Cartn_z>
         <PDBx:pdbx_model_Cartn_x_ideal>-1.598</PDBx:pdbx_model_Cartn_x_ideal>
         <PDBx:pdbx_model_Cartn_y_ideal>1.022</PDBx:pdbx_model_Cartn_y_ideal>
         <PDBx:pdbx_model_Cartn_z_ideal>4.844</PDBx:pdbx_model_Cartn_z_ideal>
         <PDBx:pdbx_component_atom_id>OP1</PDBx:pdbx_component_atom_id>
         <PDBx:pdbx_component_comp_id>G</PDBx:pdbx_component_comp_id>
         <PDBx:pdbx_ordinal>3</PDBx:pdbx_ordinal>
      </PDBx:chem_comp_atom>
      <PDBx:chem_comp_atom comp_id="G" atom_id="OP2">
         <PDBx:alt_atom_id>O2P</PDBx:alt_atom_id>
         <PDBx:type_symbol>O</PDBx:type_symbol>
         <PDBx:charge>0</PDBx:charge>
         <PDBx:pdbx_align>1</PDBx:pdbx_align>
         <PDBx:pdbx_aromatic_flag>N</PDBx:pdbx_aromatic_flag>
         <PDBx:pdbx_leaving_atom_flag>N</PDBx:pdbx_leaving_atom_flag>
         <PDBx:pdbx_stereo_config>N</PDBx:pdbx_stereo_config>
         <PDBx:model_Cartn_x>34.442</PDBx:model_Cartn_x>
         <PDBx:model_Cartn_y>4.727</PDBx:model_Cartn_y>
         <PDBx:model_Cartn_z>1.661</PDBx:model_Cartn_z>
         <PDBx:pdbx_model_Cartn_x_ideal>0.325</PDBx:pdbx_model_Cartn_x_ideal>
         <PDBx:pdbx_model_Cartn_y_ideal>-0.105</PDBx:pdbx_model_Cartn_y_ideal>
         <PDBx:pdbx_model_Cartn_z_ideal>6.025</PDBx:pdbx_model_Cartn_z_ideal>
         <PDBx:pdbx_component_atom_id>OP2</PDBx:pdbx_component_atom_id>
         <PDBx:pdbx_component_comp_id>G</PDBx:pdbx_component_comp_id>
         <PDBx:pdbx_ordinal>4</PDBx:pdbx_ordinal>
      </PDBx:chem_comp_atom>
      <PDBx:chem_comp_atom comp_id="G" atom_id="O5&apos;">
         <PDBx:alt_atom_id>O5*</PDBx:alt_atom_id>
         <PDBx:type_symbol>O</PDBx:type_symbol>
         <PDBx:charge>0</PDBx:charge>
         <PDBx:pdbx_align>1</PDBx:pdbx_align>
         <PDBx:pdbx_aromatic_flag>N</PDBx:pdbx_aromatic_flag>
         <PDBx:pdbx_leaving_atom_flag>N</PDBx:pdbx_leaving_atom_flag>
         <PDBx:pdbx_stereo_config>N</PDBx:pdbx_stereo_config>
         <PDBx:model_Cartn_x>32.289</PDBx:model_Cartn_x>
         <PDBx:model_Cartn_y>3.932</PDBx:model_Cartn_y>
         <PDBx:model_Cartn_z>0.811</PDBx:model_Cartn_z>
         <PDBx:pdbx_model_Cartn_x_ideal>-0.365</PDBx:pdbx_model_Cartn_x_ideal>
         <PDBx:pdbx_model_Cartn_y_ideal>-0.780</PDBx:pdbx_model_Cartn_y_ideal>
         <PDBx:pdbx_model_Cartn_z_ideal>3.580</PDBx:pdbx_model_Cartn_z_ideal>
         <PDBx:pdbx_component_atom_id>O5&apos;</PDBx:pdbx_component_atom_id>
         <PDBx:pdbx_component_comp_id>G</PDBx:pdbx_component_comp_id>
         <PDBx:pdbx_ordinal>5</PDBx:pdbx_ordinal>
      </PDBx:chem_comp_atom>
      <PDBx:chem_comp_atom comp_id="G" atom_id="C5&apos;">
         <PDBx:alt_atom_id>C5*</PDBx:alt_atom_id>
         <PDBx:type_symbol>C</PDBx:type_symbol>
         <PDBx:charge>0</PDBx:charge>
         <PDBx:pdbx_align>1</PDBx:pdbx_align>
         <PDBx:pdbx_aromatic_flag>N</PDBx:pdbx_aromatic_flag>
         <PDBx:pdbx_leaving_atom_flag>N</PDBx:pdbx_leaving_atom_flag>
         <PDBx:pdbx_stereo_config>N</PDBx:pdbx_stereo_config>
         <PDBx:model_Cartn_x>32.101</PDBx:model_Cartn_x>
         <PDBx:model_Cartn_y>2.551</PDBx:model_Cartn_y>
         <PDBx:model_Cartn_z>1.198</PDBx:model_Cartn_z>
         <PDBx:pdbx_model_Cartn_x_ideal>0.542</PDBx:pdbx_model_Cartn_x_ideal>
         <PDBx:pdbx_model_Cartn_y_ideal>0.217</PDBx:pdbx_model_Cartn_y_ideal>
         <PDBx:pdbx_model_Cartn_z_ideal>3.109</PDBx:pdbx_model_Cartn_z_ideal>
         <PDBx:pdbx_component_atom_id>C5&apos;</PDBx:pdbx_component_atom_id>
         <PDBx:pdbx_component_comp_id>G</PDBx:pdbx_component_comp_id>
         <PDBx:pdbx_ordinal>6</PDBx:pdbx_ordinal>
      </PDBx:chem_comp_atom>
      <PDBx:chem_comp_atom comp_id="G" atom_id="C4&apos;">
         <PDBx:alt_atom_id>C4*</PDBx:alt_atom_id>
         <PDBx:type_symbol>C</PDBx:type_symbol>
         <PDBx:charge>0</PDBx:charge>
         <PDBx:pdbx_align>1</PDBx:pdbx_align>
         <PDBx:pdbx_aromatic_flag>N</PDBx:pdbx_aromatic_flag>
         <PDBx:pdbx_leaving_atom_flag>N</PDBx:pdbx_leaving_atom_flag>
         <PDBx:pdbx_stereo_config>R</PDBx:pdbx_stereo_config>
         <PDBx:model_Cartn_x>30.760</PDBx:model_Cartn_x>
         <PDBx:model_Cartn_y>2.450</PDBx:model_Cartn_y>
         <PDBx:model_Cartn_z>1.879</PDBx:model_Cartn_z>
         <PDBx:pdbx_model_Cartn_x_ideal>1.100</PDBx:pdbx_model_Cartn_x_ideal>
         <PDBx:pdbx_model_Cartn_y_ideal>-0.200</PDBx:pdbx_model_Cartn_y_ideal>
         <PDBx:pdbx_model_Cartn_z_ideal>1.748</PDBx:pdbx_model_Cartn_z_ideal>
         <PDBx:pdbx_component_atom_id>C4&apos;</PDBx:pdbx_component_atom_id>
         <PDBx:pdbx_component_comp_id>G</PDBx:pdbx_component_comp_id>
         <PDBx:pdbx_ordinal>7</PDBx:pdbx_ordinal>
      </PDBx:chem_comp_atom>
      <PDBx:chem_comp_atom comp_id="G" atom_id="O4&apos;">
         <PDBx:alt_atom_id>O4*</PDBx:alt_atom_id>
         <PDBx:type_symbol>O</PDBx:type_symbol>
         <PDBx:charge>0</PDBx:charge>
         <PDBx:pdbx_align>1</PDBx:pdbx_align>
         <PDBx:pdbx_aromatic_flag>N</PDBx:pdbx_aromatic_flag>
         <PDBx:pdbx_leaving_atom_flag>N</PDBx:pdbx_leaving_atom_flag>
         <PDBx:pdbx_stereo_config>N</PDBx:pdbx_stereo_config>
         <PDBx:model_Cartn_x>30.797</PDBx:model_Cartn_x>
         <PDBx:model_Cartn_y>3.202</PDBx:model_Cartn_y>
         <PDBx:model_Cartn_z>3.104</PDBx:model_Cartn_z>
         <PDBx:pdbx_model_Cartn_x_ideal>0.033</PDBx:pdbx_model_Cartn_x_ideal>
         <PDBx:pdbx_model_Cartn_y_ideal>-0.318</PDBx:pdbx_model_Cartn_y_ideal>
         <PDBx:pdbx_model_Cartn_z_ideal>0.782</PDBx:pdbx_model_Cartn_z_ideal>
         <PDBx:pdbx_component_atom_id>O4&apos;</PDBx:pdbx_component_atom_id>
         <PDBx:pdbx_component_comp_id>G</PDBx:pdbx_component_comp_id>
         <PDBx:pdbx_ordinal>8</PDBx:pdbx_ordinal>
      </PDBx:chem_comp_atom>
      <PDBx:chem_comp_atom comp_id="G" atom_id="C3&apos;">
         <PDBx:alt_atom_id>C3*</PDBx:alt_atom_id>
         <PDBx:type_symbol>C</PDBx:type_symbol>
         <PDBx:charge>0</PDBx:charge>
         <PDBx:pdbx_align>1</PDBx:pdbx_align>
         <PDBx:pdbx_aromatic_flag>N</PDBx:pdbx_aromatic_flag>
         <PDBx:pdbx_leaving_atom_flag>N</PDBx:pdbx_leaving_atom_flag>
         <PDBx:pdbx_stereo_config>S</PDBx:pdbx_stereo_config>
         <PDBx:model_Cartn_x>29.597</PDBx:model_Cartn_x>
         <PDBx:model_Cartn_y>3.022</PDBx:model_Cartn_y>
         <PDBx:model_Cartn_z>1.070</PDBx:model_Cartn_z>
         <PDBx:pdbx_model_Cartn_x_ideal>2.025</PDBx:pdbx_model_Cartn_x_ideal>
         <PDBx:pdbx_model_Cartn_y_ideal>0.898</PDBx:pdbx_model_Cartn_y_ideal>
         <PDBx:pdbx_model_Cartn_z_ideal>1.182</PDBx:pdbx_model_Cartn_z_ideal>
         <PDBx:pdbx_component_atom_id>C3&apos;</PDBx:pdbx_component_atom_id>
         <PDBx:pdbx_component_comp_id>G</PDBx:pdbx_component_comp_id>
         <PDBx:pdbx_ordinal>9</PDBx:pdbx_ordinal>
      </PDBx:chem_comp_atom>
      <PDBx:chem_comp_atom comp_id="G" atom_id="O3&apos;">
         <PDBx:alt_atom_id>O3*</PDBx:alt_atom_id>
         <PDBx:type_symbol>O</PDBx:type_symbol>
         <PDBx:charge>0</PDBx:charge>
         <PDBx:pdbx_align>1</PDBx:pdbx_align>
         <PDBx:pdbx_aromatic_flag>N</PDBx:pdbx_aromatic_flag>
         <PDBx:pdbx_leaving_atom_flag>N</PDBx:pdbx_leaving_atom_flag>
         <PDBx:pdbx_stereo_config>N</PDBx:pdbx_stereo_config>
         <PDBx:model_Cartn_x>29.106</PDBx:model_Cartn_x>
         <PDBx:model_Cartn_y>2.045</PDBx:model_Cartn_y>
         <PDBx:model_Cartn_z>0.152</PDBx:model_Cartn_z>
         <PDBx:pdbx_model_Cartn_x_ideal>3.395</PDBx:pdbx_model_Cartn_x_ideal>
         <PDBx:pdbx_model_Cartn_y_ideal>0.582</PDBx:pdbx_model_Cartn_y_ideal>
         <PDBx:pdbx_model_Cartn_z_ideal>1.439</PDBx:pdbx_model_Cartn_z_ideal>
         <PDBx:pdbx_component_atom_id>O3&apos;</PDBx:pdbx_component_atom_id>
         <PDBx:pdbx_component_comp_id>G</PDBx:pdbx_component_comp_id>
         <PDBx:pdbx_ordinal>10</PDBx:pdbx_ordinal>
      </PDBx:chem_comp_atom>
      <PDBx:chem_comp_atom comp_id="G" atom_id="C2&apos;">
         <PDBx:alt_atom_id>C2*</PDBx:alt_atom_id>
         <PDBx:type_symbol>C</PDBx:type_symbol>
         <PDBx:charge>0</PDBx:charge>
         <PDBx:pdbx_align>1</PDBx:pdbx_align>
         <PDBx:pdbx_aromatic_flag>N</PDBx:pdbx_aromatic_flag>
         <PDBx:pdbx_leaving_atom_flag>N</PDBx:pdbx_leaving_atom_flag>
         <PDBx:pdbx_stereo_config>R</PDBx:pdbx_stereo_config>
         <PDBx:model_Cartn_x>28.603</PDBx:model_Cartn_x>
         <PDBx:model_Cartn_y>3.421</PDBx:model_Cartn_y>
         <PDBx:model_Cartn_z>2.118</PDBx:model_Cartn_z>
         <PDBx:pdbx_model_Cartn_x_ideal>1.741</PDBx:pdbx_model_Cartn_x_ideal>
         <PDBx:pdbx_model_Cartn_y_ideal>0.884</PDBx:pdbx_model_Cartn_y_ideal>
         <PDBx:pdbx_model_Cartn_z_ideal>-0.338</PDBx:pdbx_model_Cartn_z_ideal>
         <PDBx:pdbx_component_atom_id>C2&apos;</PDBx:pdbx_component_atom_id>
         <PDBx:pdbx_component_comp_id>G</PDBx:pdbx_component_comp_id>
         <PDBx:pdbx_ordinal>11</PDBx:pdbx_ordinal>
      </PDBx:chem_comp_atom>
      <PDBx:chem_comp_atom comp_id="G" atom_id="O2&apos;">
         <PDBx:alt_atom_id>O2*</PDBx:alt_atom_id>
         <PDBx:type_symbol>O</PDBx:type_symbol>
         <PDBx:charge>0</PDBx:charge>
         <PDBx:pdbx_align>1</PDBx:pdbx_align>
         <PDBx:pdbx_aromatic_flag>N</PDBx:pdbx_aromatic_flag>
         <PDBx:pdbx_leaving_atom_flag>N</PDBx:pdbx_leaving_atom_flag>
         <PDBx:pdbx_stereo_config>N</PDBx:pdbx_stereo_config>
         <PDBx:model_Cartn_x>27.930</PDBx:model_Cartn_x>
         <PDBx:model_Cartn_y>2.319</PDBx:model_Cartn_y>
         <PDBx:model_Cartn_z>2.657</PDBx:model_Cartn_z>
         <PDBx:pdbx_model_Cartn_x_ideal>2.927</PDBx:pdbx_model_Cartn_x_ideal>
         <PDBx:pdbx_model_Cartn_y_ideal>0.560</PDBx:pdbx_model_Cartn_y_ideal>
         <PDBx:pdbx_model_Cartn_z_ideal>-1.066</PDBx:pdbx_model_Cartn_z_ideal>
         <PDBx:pdbx_component_atom_id>O2&apos;</PDBx:pdbx_component_atom_id>
         <PDBx:pdbx_component_comp_id>G</PDBx:pdbx_component_comp_id>
         <PDBx:pdbx_ordinal>12</PDBx:pdbx_ordinal>
      </PDBx:chem_comp_atom>
      <PDBx:chem_comp_atom comp_id="G" atom_id="C1&apos;">
         <PDBx:alt_atom_id>C1*</PDBx:alt_atom_id>
         <PDBx:type_symbol>C</PDBx:type_symbol>
         <PDBx:charge>0</PDBx:charge>
         <PDBx:pdbx_align>1</PDBx:pdbx_align>
         <PDBx:pdbx_aromatic_flag>N</PDBx:pdbx_aromatic_flag>
         <PDBx:pdbx_leaving_atom_flag>N</PDBx:pdbx_leaving_atom_flag>
         <PDBx:pdbx_stereo_config>R</PDBx:pdbx_stereo_config>
         <PDBx:model_Cartn_x>29.487</PDBx:model_Cartn_x>
         <PDBx:model_Cartn_y>3.936</PDBx:model_Cartn_y>
         <PDBx:model_Cartn_z>3.170</PDBx:model_Cartn_z>
         <PDBx:pdbx_model_Cartn_x_ideal>0.675</PDBx:pdbx_model_Cartn_x_ideal>
         <PDBx:pdbx_model_Cartn_y_ideal>-0.220</PDBx:pdbx_model_Cartn_y_ideal>
         <PDBx:pdbx_model_Cartn_z_ideal>-0.507</PDBx:pdbx_model_Cartn_z_ideal>
         <PDBx:pdbx_component_atom_id>C1&apos;</PDBx:pdbx_component_atom_id>
         <PDBx:pdbx_component_comp_id>G</PDBx:pdbx_component_comp_id>
         <PDBx:pdbx_ordinal>13</PDBx:pdbx_ordinal>
      </PDBx:chem_comp_atom>
      <PDBx:chem_comp_atom comp_id="G" atom_id="N9">
         <PDBx:alt_atom_id>N9</PDBx:alt_atom_id>
         <PDBx:type_symbol>N</PDBx:type_symbol>
         <PDBx:charge>0</PDBx:charge>
         <PDBx:pdbx_align>1</PDBx:pdbx_align>
         <PDBx:pdbx_aromatic_flag>Y</PDBx:pdbx_aromatic_flag>
         <PDBx:pdbx_leaving_atom_flag>N</PDBx:pdbx_leaving_atom_flag>
         <PDBx:pdbx_stereo_config>N</PDBx:pdbx_stereo_config>
         <PDBx:model_Cartn_x>29.942</PDBx:model_Cartn_x>
         <PDBx:model_Cartn_y>5.378</PDBx:model_Cartn_y>
         <PDBx:model_Cartn_z>3.195</PDBx:model_Cartn_z>
         <PDBx:pdbx_model_Cartn_x_ideal>-0.297</PDBx:pdbx_model_Cartn_x_ideal>
         <PDBx:pdbx_model_Cartn_y_ideal>0.162</PDBx:pdbx_model_Cartn_y_ideal>
         <PDBx:pdbx_model_Cartn_z_ideal>-1.534</PDBx:pdbx_model_Cartn_z_ideal>
         <PDBx:pdbx_component_atom_id>N9</PDBx:pdbx_component_atom_id>
         <PDBx:pdbx_component_comp_id>G</PDBx:pdbx_component_comp_id>
         <PDBx:pdbx_ordinal>14</PDBx:pdbx_ordinal>
      </PDBx:chem_comp_atom>
      <PDBx:chem_comp_atom comp_id="G" atom_id="C8">
         <PDBx:alt_atom_id>C8</PDBx:alt_atom_id>
         <PDBx:type_symbol>C</PDBx:type_symbol>
         <PDBx:charge>0</PDBx:charge>
         <PDBx:pdbx_align>1</PDBx:pdbx_align>
         <PDBx:pdbx_aromatic_flag>Y</PDBx:pdbx_aromatic_flag>
         <PDBx:pdbx_leaving_atom_flag>N</PDBx:pdbx_leaving_atom_flag>
         <PDBx:pdbx_stereo_config>N</PDBx:pdbx_stereo_config>
         <PDBx:model_Cartn_x>31.187</PDBx:model_Cartn_x>
         <PDBx:model_Cartn_y>5.907</PDBx:model_Cartn_y>
         <PDBx:model_Cartn_z>3.065</PDBx:model_Cartn_z>
         <PDBx:pdbx_model_Cartn_x_ideal>-1.440</PDBx:pdbx_model_Cartn_x_ideal>
         <PDBx:pdbx_model_Cartn_y_ideal>0.880</PDBx:pdbx_model_Cartn_y_ideal>
         <PDBx:pdbx_model_Cartn_z_ideal>-1.334</PDBx:pdbx_model_Cartn_z_ideal>
         <PDBx:pdbx_component_atom_id>C8</PDBx:pdbx_component_atom_id>
         <PDBx:pdbx_component_comp_id>G</PDBx:pdbx_component_comp_id>
         <PDBx:pdbx_ordinal>15</PDBx:pdbx_ordinal>
      </PDBx:chem_comp_atom>
      <PDBx:chem_comp_atom comp_id="G" atom_id="N7">
         <PDBx:alt_atom_id>N7</PDBx:alt_atom_id>
         <PDBx:type_symbol>N</PDBx:type_symbol>
         <PDBx:charge>0</PDBx:charge>
         <PDBx:pdbx_align>1</PDBx:pdbx_align>
         <PDBx:pdbx_aromatic_flag>Y</PDBx:pdbx_aromatic_flag>
         <PDBx:pdbx_leaving_atom_flag>N</PDBx:pdbx_leaving_atom_flag>
         <PDBx:pdbx_stereo_config>N</PDBx:pdbx_stereo_config>
         <PDBx:model_Cartn_x>31.237</PDBx:model_Cartn_x>
         <PDBx:model_Cartn_y>7.191</PDBx:model_Cartn_y>
         <PDBx:model_Cartn_z>3.136</PDBx:model_Cartn_z>
         <PDBx:pdbx_model_Cartn_x_ideal>-2.066</PDBx:pdbx_model_Cartn_x_ideal>
         <PDBx:pdbx_model_Cartn_y_ideal>1.037</PDBx:pdbx_model_Cartn_y_ideal>
         <PDBx:pdbx_model_Cartn_z_ideal>-2.464</PDBx:pdbx_model_Cartn_z_ideal>
         <PDBx:pdbx_component_atom_id>N7</PDBx:pdbx_component_atom_id>
         <PDBx:pdbx_component_comp_id>G</PDBx:pdbx_component_comp_id>
         <PDBx:pdbx_ordinal>16</PDBx:pdbx_ordinal>
      </PDBx:chem_comp_atom>
      <PDBx:chem_comp_atom comp_id="G" atom_id="C5">
         <PDBx:alt_atom_id>C5</PDBx:alt_atom_id>
         <PDBx:type_symbol>C</PDBx:type_symbol>
         <PDBx:charge>0</PDBx:charge>
         <PDBx:pdbx_align>1</PDBx:pdbx_align>
         <PDBx:pdbx_aromatic_flag>Y</PDBx:pdbx_aromatic_flag>
         <PDBx:pdbx_leaving_atom_flag>N</PDBx:pdbx_leaving_atom_flag>
         <PDBx:pdbx_stereo_config>N</PDBx:pdbx_stereo_config>
         <PDBx:model_Cartn_x>29.896</PDBx:model_Cartn_x>
         <PDBx:model_Cartn_y>7.536</PDBx:model_Cartn_y>
         <PDBx:model_Cartn_z>3.341</PDBx:model_Cartn_z>
         <PDBx:pdbx_model_Cartn_x_ideal>-1.364</PDBx:pdbx_model_Cartn_x_ideal>
         <PDBx:pdbx_model_Cartn_y_ideal>0.431</PDBx:pdbx_model_Cartn_y_ideal>
         <PDBx:pdbx_model_Cartn_z_ideal>-3.453</PDBx:pdbx_model_Cartn_z_ideal>
         <PDBx:pdbx_component_atom_id>C5</PDBx:pdbx_component_atom_id>
         <PDBx:pdbx_component_comp_id>G</PDBx:pdbx_component_comp_id>
         <PDBx:pdbx_ordinal>17</PDBx:pdbx_ordinal>
      </PDBx:chem_comp_atom>
      <PDBx:chem_comp_atom comp_id="G" atom_id="C6">
         <PDBx:alt_atom_id>C6</PDBx:alt_atom_id>
         <PDBx:type_symbol>C</PDBx:type_symbol>
         <PDBx:charge>0</PDBx:charge>
         <PDBx:pdbx_align>1</PDBx:pdbx_align>
         <PDBx:pdbx_aromatic_flag>N</PDBx:pdbx_aromatic_flag>
         <PDBx:pdbx_leaving_atom_flag>N</PDBx:pdbx_leaving_atom_flag>
         <PDBx:pdbx_stereo_config>N</PDBx:pdbx_stereo_config>
         <PDBx:model_Cartn_x>29.331</PDBx:model_Cartn_x>
         <PDBx:model_Cartn_y>8.813</PDBx:model_Cartn_y>
         <PDBx:model_Cartn_z>3.503</PDBx:model_Cartn_z>
         <PDBx:pdbx_model_Cartn_x_ideal>-1.556</PDBx:pdbx_model_Cartn_x_ideal>
         <PDBx:pdbx_model_Cartn_y_ideal>0.279</PDBx:pdbx_model_Cartn_y_ideal>
         <PDBx:pdbx_model_Cartn_z_ideal>-4.846</PDBx:pdbx_model_Cartn_z_ideal>
         <PDBx:pdbx_component_atom_id>C6</PDBx:pdbx_component_atom_id>
         <PDBx:pdbx_component_comp_id>G</PDBx:pdbx_component_comp_id>
         <PDBx:pdbx_ordinal>18</PDBx:pdbx_ordinal>
      </PDBx:chem_comp_atom>
      <PDBx:chem_comp_atom comp_id="G" atom_id="O6">
         <PDBx:alt_atom_id>O6</PDBx:alt_atom_id>
         <PDBx:type_symbol>O</PDBx:type_symbol>
         <PDBx:charge>0</PDBx:charge>
         <PDBx:pdbx_align>1</PDBx:pdbx_align>
         <PDBx:pdbx_aromatic_flag>N</PDBx:pdbx_aromatic_flag>
         <PDBx:pdbx_leaving_atom_flag>N</PDBx:pdbx_leaving_atom_flag>
         <PDBx:pdbx_stereo_config>N</PDBx:pdbx_stereo_config>
         <PDBx:model_Cartn_x>29.901</PDBx:model_Cartn_x>
         <PDBx:model_Cartn_y>9.926</PDBx:model_Cartn_y>
         <PDBx:model_Cartn_z>3.495</PDBx:model_Cartn_z>
         <PDBx:pdbx_model_Cartn_x_ideal>-2.534</PDBx:pdbx_model_Cartn_x_ideal>
         <PDBx:pdbx_model_Cartn_y_ideal>0.755</PDBx:pdbx_model_Cartn_y_ideal>
         <PDBx:pdbx_model_Cartn_z_ideal>-5.397</PDBx:pdbx_model_Cartn_z_ideal>
         <PDBx:pdbx_component_atom_id>O6</PDBx:pdbx_component_atom_id>
         <PDBx:pdbx_component_comp_id>G</PDBx:pdbx_component_comp_id>
         <PDBx:pdbx_ordinal>19</PDBx:pdbx_ordinal>
      </PDBx:chem_comp_atom>
      <PDBx:chem_comp_atom comp_id="G" atom_id="N1">
         <PDBx:alt_atom_id>N1</PDBx:alt_atom_id>
         <PDBx:type_symbol>N</PDBx:type_symbol>
         <PDBx:charge>0</PDBx:charge>
         <PDBx:pdbx_align>1</PDBx:pdbx_align>
         <PDBx:pdbx_aromatic_flag>N</PDBx:pdbx_aromatic_flag>
         <PDBx:pdbx_leaving_atom_flag>N</PDBx:pdbx_leaving_atom_flag>
         <PDBx:pdbx_stereo_config>N</PDBx:pdbx_stereo_config>
         <PDBx:model_Cartn_x>27.948</PDBx:model_Cartn_x>
         <PDBx:model_Cartn_y>8.749</PDBx:model_Cartn_y>
         <PDBx:model_Cartn_z>3.683</PDBx:model_Cartn_z>
         <PDBx:pdbx_model_Cartn_x_ideal>-0.626</PDBx:pdbx_model_Cartn_x_ideal>
         <PDBx:pdbx_model_Cartn_y_ideal>-0.401</PDBx:pdbx_model_Cartn_y_ideal>
         <PDBx:pdbx_model_Cartn_z_ideal>-5.551</PDBx:pdbx_model_Cartn_z_ideal>
         <PDBx:pdbx_component_atom_id>N1</PDBx:pdbx_component_atom_id>
         <PDBx:pdbx_component_comp_id>G</PDBx:pdbx_component_comp_id>
         <PDBx:pdbx_ordinal>20</PDBx:pdbx_ordinal>
      </PDBx:chem_comp_atom>
      <PDBx:chem_comp_atom comp_id="G" atom_id="C2">
         <PDBx:alt_atom_id>C2</PDBx:alt_atom_id>
         <PDBx:type_symbol>C</PDBx:type_symbol>
         <PDBx:charge>0</PDBx:charge>
         <PDBx:pdbx_align>1</PDBx:pdbx_align>
         <PDBx:pdbx_aromatic_flag>N</PDBx:pdbx_aromatic_flag>
         <PDBx:pdbx_leaving_atom_flag>N</PDBx:pdbx_leaving_atom_flag>
         <PDBx:pdbx_stereo_config>N</PDBx:pdbx_stereo_config>
         <PDBx:model_Cartn_x>27.233</PDBx:model_Cartn_x>
         <PDBx:model_Cartn_y>7.615</PDBx:model_Cartn_y>
         <PDBx:model_Cartn_z>3.707</PDBx:model_Cartn_z>
         <PDBx:pdbx_model_Cartn_x_ideal>0.459</PDBx:pdbx_model_Cartn_x_ideal>
         <PDBx:pdbx_model_Cartn_y_ideal>-0.934</PDBx:pdbx_model_Cartn_y_ideal>
         <PDBx:pdbx_model_Cartn_z_ideal>-4.923</PDBx:pdbx_model_Cartn_z_ideal>
         <PDBx:pdbx_component_atom_id>C2</PDBx:pdbx_component_atom_id>
         <PDBx:pdbx_component_comp_id>G</PDBx:pdbx_component_comp_id>
         <PDBx:pdbx_ordinal>21</PDBx:pdbx_ordinal>
      </PDBx:chem_comp_atom>
      <PDBx:chem_comp_atom comp_id="G" atom_id="N2">
         <PDBx:alt_atom_id>N2</PDBx:alt_atom_id>
         <PDBx:type_symbol>N</PDBx:type_symbol>
         <PDBx:charge>0</PDBx:charge>
         <PDBx:pdbx_align>1</PDBx:pdbx_align>
         <PDBx:pdbx_aromatic_flag>N</PDBx:pdbx_aromatic_flag>
         <PDBx:pdbx_leaving_atom_flag>N</PDBx:pdbx_leaving_atom_flag>
         <PDBx:pdbx_stereo_config>N</PDBx:pdbx_stereo_config>
         <PDBx:model_Cartn_x>25.894</PDBx:model_Cartn_x>
         <PDBx:model_Cartn_y>7.743</PDBx:model_Cartn_y>
         <PDBx:model_Cartn_z>3.899</PDBx:model_Cartn_z>
         <PDBx:pdbx_model_Cartn_x_ideal>1.384</PDBx:pdbx_model_Cartn_x_ideal>
         <PDBx:pdbx_model_Cartn_y_ideal>-1.626</PDBx:pdbx_model_Cartn_y_ideal>
         <PDBx:pdbx_model_Cartn_z_ideal>-5.664</PDBx:pdbx_model_Cartn_z_ideal>
         <PDBx:pdbx_component_atom_id>N2</PDBx:pdbx_component_atom_id>
         <PDBx:pdbx_component_comp_id>G</PDBx:pdbx_component_comp_id>
         <PDBx:pdbx_ordinal>22</PDBx:pdbx_ordinal>
      </PDBx:chem_comp_atom>
      <PDBx:chem_comp_atom comp_id="G" atom_id="N3">
         <PDBx:alt_atom_id>N3</PDBx:alt_atom_id>
         <PDBx:type_symbol>N</PDBx:type_symbol>
         <PDBx:charge>0</PDBx:charge>
         <PDBx:pdbx_align>1</PDBx:pdbx_align>
         <PDBx:pdbx_aromatic_flag>N</PDBx:pdbx_aromatic_flag>
         <PDBx:pdbx_leaving_atom_flag>N</PDBx:pdbx_leaving_atom_flag>
         <PDBx:pdbx_stereo_config>N</PDBx:pdbx_stereo_config>
         <PDBx:model_Cartn_x>27.758</PDBx:model_Cartn_x>
         <PDBx:model_Cartn_y>6.393</PDBx:model_Cartn_y>
         <PDBx:model_Cartn_z>3.559</PDBx:model_Cartn_z>
         <PDBx:pdbx_model_Cartn_x_ideal>0.649</PDBx:pdbx_model_Cartn_x_ideal>
         <PDBx:pdbx_model_Cartn_y_ideal>-0.800</PDBx:pdbx_model_Cartn_y_ideal>
         <PDBx:pdbx_model_Cartn_z_ideal>-3.630</PDBx:pdbx_model_Cartn_z_ideal>
         <PDBx:pdbx_component_atom_id>N3</PDBx:pdbx_component_atom_id>
         <PDBx:pdbx_component_comp_id>G</PDBx:pdbx_component_comp_id>
         <PDBx:pdbx_ordinal>23</PDBx:pdbx_ordinal>
      </PDBx:chem_comp_atom>
      <PDBx:chem_comp_atom comp_id="G" atom_id="C4">
         <PDBx:alt_atom_id>C4</PDBx:alt_atom_id>
         <PDBx:type_symbol>C</PDBx:type_symbol>
         <PDBx:charge>0</PDBx:charge>
         <PDBx:pdbx_align>1</PDBx:pdbx_align>
         <PDBx:pdbx_aromatic_flag>Y</PDBx:pdbx_aromatic_flag>
         <PDBx:pdbx_leaving_atom_flag>N</PDBx:pdbx_leaving_atom_flag>
         <PDBx:pdbx_stereo_config>N</PDBx:pdbx_stereo_config>
         <PDBx:model_Cartn_x>29.079</PDBx:model_Cartn_x>
         <PDBx:model_Cartn_y>6.431</PDBx:model_Cartn_y>
         <PDBx:model_Cartn_z>3.382</PDBx:model_Cartn_z>
         <PDBx:pdbx_model_Cartn_x_ideal>-0.226</PDBx:pdbx_model_Cartn_x_ideal>
         <PDBx:pdbx_model_Cartn_y_ideal>-0.134</PDBx:pdbx_model_Cartn_y_ideal>
         <PDBx:pdbx_model_Cartn_z_ideal>-2.868</PDBx:pdbx_model_Cartn_z_ideal>
         <PDBx:pdbx_component_atom_id>C4</PDBx:pdbx_component_atom_id>
         <PDBx:pdbx_component_comp_id>G</PDBx:pdbx_component_comp_id>
         <PDBx:pdbx_ordinal>24</PDBx:pdbx_ordinal>
      </PDBx:chem_comp_atom>
      <PDBx:chem_comp_atom comp_id="G" atom_id="HOP3">
         <PDBx:alt_atom_id>3HOP</PDBx:alt_atom_id>
         <PDBx:type_symbol>H</PDBx:type_symbol>
         <PDBx:charge>0</PDBx:charge>
         <PDBx:pdbx_align>0</PDBx:pdbx_align>
         <PDBx:pdbx_aromatic_flag>N</PDBx:pdbx_aromatic_flag>
         <PDBx:pdbx_leaving_atom_flag>N</PDBx:pdbx_leaving_atom_flag>
         <PDBx:pdbx_stereo_config>N</PDBx:pdbx_stereo_config>
         <PDBx:model_Cartn_x>34.442</PDBx:model_Cartn_x>
         <PDBx:model_Cartn_y>2.528</PDBx:model_Cartn_y>
         <PDBx:model_Cartn_z>0.096</PDBx:model_Cartn_z>
         <PDBx:pdbx_model_Cartn_x_ideal>-2.247</PDBx:pdbx_model_Cartn_x_ideal>
         <PDBx:pdbx_model_Cartn_y_ideal>-1.021</PDBx:pdbx_model_Cartn_y_ideal>
         <PDBx:pdbx_model_Cartn_z_ideal>6.453</PDBx:pdbx_model_Cartn_z_ideal>
         <PDBx:pdbx_component_atom_id>HOP3</PDBx:pdbx_component_atom_id>
         <PDBx:pdbx_component_comp_id>G</PDBx:pdbx_component_comp_id>
         <PDBx:pdbx_ordinal>25</PDBx:pdbx_ordinal>
      </PDBx:chem_comp_atom>
      <PDBx:chem_comp_atom comp_id="G" atom_id="HOP2">
         <PDBx:alt_atom_id>2HOP</PDBx:alt_atom_id>
         <PDBx:type_symbol>H</PDBx:type_symbol>
         <PDBx:charge>0</PDBx:charge>
         <PDBx:pdbx_align>0</PDBx:pdbx_align>
         <PDBx:pdbx_aromatic_flag>N</PDBx:pdbx_aromatic_flag>
         <PDBx:pdbx_leaving_atom_flag>N</PDBx:pdbx_leaving_atom_flag>
         <PDBx:pdbx_stereo_config>N</PDBx:pdbx_stereo_config>
         <PDBx:model_Cartn_x>34.571</PDBx:model_Cartn_x>
         <PDBx:model_Cartn_y>3.941</PDBx:model_Cartn_y>
         <PDBx:model_Cartn_z>2.179</PDBx:model_Cartn_z>
         <PDBx:pdbx_model_Cartn_x_ideal>0.745</PDBx:pdbx_model_Cartn_x_ideal>
         <PDBx:pdbx_model_Cartn_y_ideal>-0.973</PDBx:pdbx_model_Cartn_y_ideal>
         <PDBx:pdbx_model_Cartn_z_ideal>6.104</PDBx:pdbx_model_Cartn_z_ideal>
         <PDBx:pdbx_component_atom_id>HOP2</PDBx:pdbx_component_atom_id>
         <PDBx:pdbx_component_comp_id>G</PDBx:pdbx_component_comp_id>
         <PDBx:pdbx_ordinal>26</PDBx:pdbx_ordinal>
      </PDBx:chem_comp_atom>
      <PDBx:chem_comp_atom comp_id="G" atom_id="H5&apos;">
         <PDBx:alt_atom_id>1H5*</PDBx:alt_atom_id>
         <PDBx:type_symbol>H</PDBx:type_symbol>
         <PDBx:charge>0</PDBx:charge>
         <PDBx:pdbx_align>1</PDBx:pdbx_align>
         <PDBx:pdbx_aromatic_flag>N</PDBx:pdbx_aromatic_flag>
         <PDBx:pdbx_leaving_atom_flag>N</PDBx:pdbx_leaving_atom_flag>
         <PDBx:pdbx_stereo_config>N</PDBx:pdbx_stereo_config>
         <PDBx:model_Cartn_x>32.209</PDBx:model_Cartn_x>
         <PDBx:model_Cartn_y>1.841</PDBx:model_Cartn_y>
         <PDBx:model_Cartn_z>0.344</PDBx:model_Cartn_z>
         <PDBx:pdbx_model_Cartn_x_ideal>1.362</PDBx:pdbx_model_Cartn_x_ideal>
         <PDBx:pdbx_model_Cartn_y_ideal>0.327</PDBx:pdbx_model_Cartn_y_ideal>
         <PDBx:pdbx_model_Cartn_z_ideal>3.820</PDBx:pdbx_model_Cartn_z_ideal>
         <PDBx:pdbx_component_atom_id>H5&apos;</PDBx:pdbx_component_atom_id>
         <PDBx:pdbx_component_comp_id>G</PDBx:pdbx_component_comp_id>
         <PDBx:pdbx_ordinal>27</PDBx:pdbx_ordinal>
      </PDBx:chem_comp_atom>
      <PDBx:chem_comp_atom comp_id="G" atom_id="H5&apos;&apos;">
         <PDBx:alt_atom_id>2H5*</PDBx:alt_atom_id>
         <PDBx:type_symbol>H</PDBx:type_symbol>
         <PDBx:charge>0</PDBx:charge>
         <PDBx:pdbx_align>0</PDBx:pdbx_align>
         <PDBx:pdbx_aromatic_flag>N</PDBx:pdbx_aromatic_flag>
         <PDBx:pdbx_leaving_atom_flag>N</PDBx:pdbx_leaving_atom_flag>
         <PDBx:pdbx_stereo_config>N</PDBx:pdbx_stereo_config>
         <PDBx:model_Cartn_x>32.936</PDBx:model_Cartn_x>
         <PDBx:model_Cartn_y>2.156</PDBx:model_Cartn_y>
         <PDBx:model_Cartn_z>1.822</PDBx:model_Cartn_z>
         <PDBx:pdbx_model_Cartn_x_ideal>0.018</PDBx:pdbx_model_Cartn_x_ideal>
         <PDBx:pdbx_model_Cartn_y_ideal>1.168</PDBx:pdbx_model_Cartn_y_ideal>
         <PDBx:pdbx_model_Cartn_z_ideal>3.011</PDBx:pdbx_model_Cartn_z_ideal>
         <PDBx:pdbx_component_atom_id>H5&apos;&apos;</PDBx:pdbx_component_atom_id>
         <PDBx:pdbx_component_comp_id>G</PDBx:pdbx_component_comp_id>
         <PDBx:pdbx_ordinal>28</PDBx:pdbx_ordinal>
      </PDBx:chem_comp_atom>
      <PDBx:chem_comp_atom comp_id="G" atom_id="H4&apos;">
         <PDBx:alt_atom_id>H4*</PDBx:alt_atom_id>
         <PDBx:type_symbol>H</PDBx:type_symbol>
         <PDBx:charge>0</PDBx:charge>
         <PDBx:pdbx_align>1</PDBx:pdbx_align>
         <PDBx:pdbx_aromatic_flag>N</PDBx:pdbx_aromatic_flag>
         <PDBx:pdbx_leaving_atom_flag>N</PDBx:pdbx_leaving_atom_flag>
         <PDBx:pdbx_stereo_config>N</PDBx:pdbx_stereo_config>
         <PDBx:model_Cartn_x>30.585</PDBx:model_Cartn_x>
         <PDBx:model_Cartn_y>1.358</PDBx:model_Cartn_y>
         <PDBx:model_Cartn_z>2.025</PDBx:model_Cartn_z>
         <PDBx:pdbx_model_Cartn_x_ideal>1.640</PDBx:pdbx_model_Cartn_x_ideal>
         <PDBx:pdbx_model_Cartn_y_ideal>-1.144</PDBx:pdbx_model_Cartn_y_ideal>
         <PDBx:pdbx_model_Cartn_z_ideal>1.833</PDBx:pdbx_model_Cartn_z_ideal>
         <PDBx:pdbx_component_atom_id>H4&apos;</PDBx:pdbx_component_atom_id>
         <PDBx:pdbx_component_comp_id>G</PDBx:pdbx_component_comp_id>
         <PDBx:pdbx_ordinal>29</PDBx:pdbx_ordinal>
      </PDBx:chem_comp_atom>
      <PDBx:chem_comp_atom comp_id="G" atom_id="H3&apos;">
         <PDBx:alt_atom_id>H3*</PDBx:alt_atom_id>
         <PDBx:type_symbol>H</PDBx:type_symbol>
         <PDBx:charge>0</PDBx:charge>
         <PDBx:pdbx_align>1</PDBx:pdbx_align>
         <PDBx:pdbx_aromatic_flag>N</PDBx:pdbx_aromatic_flag>
         <PDBx:pdbx_leaving_atom_flag>N</PDBx:pdbx_leaving_atom_flag>
         <PDBx:pdbx_stereo_config>N</PDBx:pdbx_stereo_config>
         <PDBx:model_Cartn_x>29.867</PDBx:model_Cartn_x>
         <PDBx:model_Cartn_y>3.891</PDBx:model_Cartn_y>
         <PDBx:model_Cartn_z>0.426</PDBx:model_Cartn_z>
         <PDBx:pdbx_model_Cartn_x_ideal>1.772</PDBx:pdbx_model_Cartn_x_ideal>
         <PDBx:pdbx_model_Cartn_y_ideal>1.868</PDBx:pdbx_model_Cartn_y_ideal>
         <PDBx:pdbx_model_Cartn_z_ideal>1.610</PDBx:pdbx_model_Cartn_z_ideal>
         <PDBx:pdbx_component_atom_id>H3&apos;</PDBx:pdbx_component_atom_id>
         <PDBx:pdbx_component_comp_id>G</PDBx:pdbx_component_comp_id>
         <PDBx:pdbx_ordinal>30</PDBx:pdbx_ordinal>
      </PDBx:chem_comp_atom>
      <PDBx:chem_comp_atom comp_id="G" atom_id="HO3&apos;">
         <PDBx:alt_atom_id>H3T</PDBx:alt_atom_id>
         <PDBx:type_symbol>H</PDBx:type_symbol>
         <PDBx:charge>0</PDBx:charge>
         <PDBx:pdbx_align>0</PDBx:pdbx_align>
         <PDBx:pdbx_aromatic_flag>N</PDBx:pdbx_aromatic_flag>
         <PDBx:pdbx_leaving_atom_flag>Y</PDBx:pdbx_leaving_atom_flag>
         <PDBx:pdbx_stereo_config>N</PDBx:pdbx_stereo_config>
         <PDBx:model_Cartn_x>28.382</PDBx:model_Cartn_x>
         <PDBx:model_Cartn_y>2.400</PDBx:model_Cartn_y>
         <PDBx:model_Cartn_z>-0.351</PDBx:model_Cartn_z>
         <PDBx:pdbx_model_Cartn_x_ideal>3.923</PDBx:pdbx_model_Cartn_x_ideal>
         <PDBx:pdbx_model_Cartn_y_ideal>1.300</PDBx:pdbx_model_Cartn_y_ideal>
         <PDBx:pdbx_model_Cartn_z_ideal>1.065</PDBx:pdbx_model_Cartn_z_ideal>
         <PDBx:pdbx_component_atom_id>HO3&apos;</PDBx:pdbx_component_atom_id>
         <PDBx:pdbx_component_comp_id>G</PDBx:pdbx_component_comp_id>
         <PDBx:pdbx_ordinal>31</PDBx:pdbx_ordinal>
      </PDBx:chem_comp_atom>
      <PDBx:chem_comp_atom comp_id="G" atom_id="H2&apos;">
         <PDBx:alt_atom_id>H2*</PDBx:alt_atom_id>
         <PDBx:type_symbol>H</PDBx:type_symbol>
         <PDBx:charge>0</PDBx:charge>
         <PDBx:pdbx_align>1</PDBx:pdbx_align>
         <PDBx:pdbx_aromatic_flag>N</PDBx:pdbx_aromatic_flag>
         <PDBx:pdbx_leaving_atom_flag>N</PDBx:pdbx_leaving_atom_flag>
         <PDBx:pdbx_stereo_config>N</PDBx:pdbx_stereo_config>
         <PDBx:model_Cartn_x>27.827</PDBx:model_Cartn_x>
         <PDBx:model_Cartn_y>4.115</PDBx:model_Cartn_y>
         <PDBx:model_Cartn_z>1.719</PDBx:model_Cartn_z>
         <PDBx:pdbx_model_Cartn_x_ideal>1.346</PDBx:pdbx_model_Cartn_x_ideal>
         <PDBx:pdbx_model_Cartn_y_ideal>1.847</PDBx:pdbx_model_Cartn_y_ideal>
         <PDBx:pdbx_model_Cartn_z_ideal>-0.662</PDBx:pdbx_model_Cartn_z_ideal>
         <PDBx:pdbx_component_atom_id>H2&apos;</PDBx:pdbx_component_atom_id>
         <PDBx:pdbx_component_comp_id>G</PDBx:pdbx_component_comp_id>
         <PDBx:pdbx_ordinal>32</PDBx:pdbx_ordinal>
      </PDBx:chem_comp_atom>
      <PDBx:chem_comp_atom comp_id="G" atom_id="HO2&apos;">
         <PDBx:alt_atom_id>2HO*</PDBx:alt_atom_id>
         <PDBx:type_symbol>H</PDBx:type_symbol>
         <PDBx:charge>0</PDBx:charge>
         <PDBx:pdbx_align>0</PDBx:pdbx_align>
         <PDBx:pdbx_aromatic_flag>N</PDBx:pdbx_aromatic_flag>
         <PDBx:pdbx_leaving_atom_flag>N</PDBx:pdbx_leaving_atom_flag>
         <PDBx:pdbx_stereo_config>N</PDBx:pdbx_stereo_config>
         <PDBx:model_Cartn_x>27.299</PDBx:model_Cartn_x>
         <PDBx:model_Cartn_y>2.572</PDBx:model_Cartn_y>
         <PDBx:model_Cartn_z>3.321</PDBx:model_Cartn_z>
         <PDBx:pdbx_model_Cartn_x_ideal>3.573</PDBx:pdbx_model_Cartn_x_ideal>
         <PDBx:pdbx_model_Cartn_y_ideal>1.254</PDBx:pdbx_model_Cartn_y_ideal>
         <PDBx:pdbx_model_Cartn_z_ideal>-0.871</PDBx:pdbx_model_Cartn_z_ideal>
         <PDBx:pdbx_component_atom_id>HO2&apos;</PDBx:pdbx_component_atom_id>
         <PDBx:pdbx_component_comp_id>G</PDBx:pdbx_component_comp_id>
         <PDBx:pdbx_ordinal>33</PDBx:pdbx_ordinal>
      </PDBx:chem_comp_atom>
      <PDBx:chem_comp_atom comp_id="G" atom_id="H1&apos;">
         <PDBx:alt_atom_id>H1*</PDBx:alt_atom_id>
         <PDBx:type_symbol>H</PDBx:type_symbol>
         <PDBx:charge>0</PDBx:charge>
         <PDBx:pdbx_align>1</PDBx:pdbx_align>
         <PDBx:pdbx_aromatic_flag>N</PDBx:pdbx_aromatic_flag>
         <PDBx:pdbx_leaving_atom_flag>N</PDBx:pdbx_leaving_atom_flag>
         <PDBx:pdbx_stereo_config>N</PDBx:pdbx_stereo_config>
         <PDBx:model_Cartn_x>28.814</PDBx:model_Cartn_x>
         <PDBx:model_Cartn_y>3.801</PDBx:model_Cartn_y>
         <PDBx:model_Cartn_z>4.048</PDBx:model_Cartn_z>
         <PDBx:pdbx_model_Cartn_x_ideal>1.148</PDBx:pdbx_model_Cartn_x_ideal>
         <PDBx:pdbx_model_Cartn_y_ideal>-1.167</PDBx:pdbx_model_Cartn_y_ideal>
         <PDBx:pdbx_model_Cartn_z_ideal>-0.769</PDBx:pdbx_model_Cartn_z_ideal>
         <PDBx:pdbx_component_atom_id>H1&apos;</PDBx:pdbx_component_atom_id>
         <PDBx:pdbx_component_comp_id>G</PDBx:pdbx_component_comp_id>
         <PDBx:pdbx_ordinal>34</PDBx:pdbx_ordinal>
      </PDBx:chem_comp_atom>
      <PDBx:chem_comp_atom comp_id="G" atom_id="H8">
         <PDBx:alt_atom_id>H8</PDBx:alt_atom_id>
         <PDBx:type_symbol>H</PDBx:type_symbol>
         <PDBx:charge>0</PDBx:charge>
         <PDBx:pdbx_align>1</PDBx:pdbx_align>
         <PDBx:pdbx_aromatic_flag>N</PDBx:pdbx_aromatic_flag>
         <PDBx:pdbx_leaving_atom_flag>N</PDBx:pdbx_leaving_atom_flag>
         <PDBx:pdbx_stereo_config>N</PDBx:pdbx_stereo_config>
         <PDBx:model_Cartn_x>32.110</PDBx:model_Cartn_x>
         <PDBx:model_Cartn_y>5.323</PDBx:model_Cartn_y>
         <PDBx:model_Cartn_z>2.909</PDBx:model_Cartn_z>
         <PDBx:pdbx_model_Cartn_x_ideal>-1.776</PDBx:pdbx_model_Cartn_x_ideal>
         <PDBx:pdbx_model_Cartn_y_ideal>1.261</PDBx:pdbx_model_Cartn_y_ideal>
         <PDBx:pdbx_model_Cartn_z_ideal>-0.381</PDBx:pdbx_model_Cartn_z_ideal>
         <PDBx:pdbx_component_atom_id>H8</PDBx:pdbx_component_atom_id>
         <PDBx:pdbx_component_comp_id>G</PDBx:pdbx_component_comp_id>
         <PDBx:pdbx_ordinal>35</PDBx:pdbx_ordinal>
      </PDBx:chem_comp_atom>
      <PDBx:chem_comp_atom comp_id="G" atom_id="H1">
         <PDBx:alt_atom_id>H1</PDBx:alt_atom_id>
         <PDBx:type_symbol>H</PDBx:type_symbol>
         <PDBx:charge>0</PDBx:charge>
         <PDBx:pdbx_align>1</PDBx:pdbx_align>
         <PDBx:pdbx_aromatic_flag>N</PDBx:pdbx_aromatic_flag>
         <PDBx:pdbx_leaving_atom_flag>N</PDBx:pdbx_leaving_atom_flag>
         <PDBx:pdbx_stereo_config>N</PDBx:pdbx_stereo_config>
         <PDBx:model_Cartn_x>27.411</PDBx:model_Cartn_x>
         <PDBx:model_Cartn_y>9.607</PDBx:model_Cartn_y>
         <PDBx:model_Cartn_z>3.808</PDBx:model_Cartn_z>
         <PDBx:pdbx_model_Cartn_x_ideal>-0.736</PDBx:pdbx_model_Cartn_x_ideal>
         <PDBx:pdbx_model_Cartn_y_ideal>-0.518</PDBx:pdbx_model_Cartn_y_ideal>
         <PDBx:pdbx_model_Cartn_z_ideal>-6.508</PDBx:pdbx_model_Cartn_z_ideal>
         <PDBx:pdbx_component_atom_id>H1</PDBx:pdbx_component_atom_id>
         <PDBx:pdbx_component_comp_id>G</PDBx:pdbx_component_comp_id>
         <PDBx:pdbx_ordinal>36</PDBx:pdbx_ordinal>
      </PDBx:chem_comp_atom>
      <PDBx:chem_comp_atom comp_id="G" atom_id="H21">
         <PDBx:alt_atom_id>1H2</PDBx:alt_atom_id>
         <PDBx:type_symbol>H</PDBx:type_symbol>
         <PDBx:charge>0</PDBx:charge>
         <PDBx:pdbx_align>1</PDBx:pdbx_align>
         <PDBx:pdbx_aromatic_flag>N</PDBx:pdbx_aromatic_flag>
         <PDBx:pdbx_leaving_atom_flag>N</PDBx:pdbx_leaving_atom_flag>
         <PDBx:pdbx_stereo_config>N</PDBx:pdbx_stereo_config>
         <PDBx:model_Cartn_x>25.350</PDBx:model_Cartn_x>
         <PDBx:model_Cartn_y>6.880</PDBx:model_Cartn_y>
         <PDBx:model_Cartn_z>3.917</PDBx:model_Cartn_z>
         <PDBx:pdbx_model_Cartn_x_ideal>2.165</PDBx:pdbx_model_Cartn_x_ideal>
         <PDBx:pdbx_model_Cartn_y_ideal>-2.007</PDBx:pdbx_model_Cartn_y_ideal>
         <PDBx:pdbx_model_Cartn_z_ideal>-5.232</PDBx:pdbx_model_Cartn_z_ideal>
         <PDBx:pdbx_component_atom_id>H21</PDBx:pdbx_component_atom_id>
         <PDBx:pdbx_component_comp_id>G</PDBx:pdbx_component_comp_id>
         <PDBx:pdbx_ordinal>37</PDBx:pdbx_ordinal>
      </PDBx:chem_comp_atom>
      <PDBx:chem_comp_atom comp_id="G" atom_id="H22">
         <PDBx:alt_atom_id>2H2</PDBx:alt_atom_id>
         <PDBx:type_symbol>H</PDBx:type_symbol>
         <PDBx:charge>0</PDBx:charge>
         <PDBx:pdbx_align>1</PDBx:pdbx_align>
         <PDBx:pdbx_aromatic_flag>N</PDBx:pdbx_aromatic_flag>
         <PDBx:pdbx_leaving_atom_flag>N</PDBx:pdbx_leaving_atom_flag>
         <PDBx:pdbx_stereo_config>N</PDBx:pdbx_stereo_config>
         <PDBx:model_Cartn_x>25.507</PDBx:model_Cartn_x>
         <PDBx:model_Cartn_y>8.377</PDBx:model_Cartn_y>
         <PDBx:model_Cartn_z>3.200</PDBx:model_Cartn_z>
         <PDBx:pdbx_model_Cartn_x_ideal>1.256</PDBx:pdbx_model_Cartn_x_ideal>
         <PDBx:pdbx_model_Cartn_y_ideal>-1.736</PDBx:pdbx_model_Cartn_y_ideal>
         <PDBx:pdbx_model_Cartn_z_ideal>-6.619</PDBx:pdbx_model_Cartn_z_ideal>
         <PDBx:pdbx_component_atom_id>H22</PDBx:pdbx_component_atom_id>
         <PDBx:pdbx_component_comp_id>G</PDBx:pdbx_component_comp_id>
         <PDBx:pdbx_ordinal>38</PDBx:pdbx_ordinal>
      </PDBx:chem_comp_atom>
   </PDBx:chem_comp_atomCategory>
   <PDBx:chem_comp_bondCategory>
      <PDBx:chem_comp_bond comp_id="G" atom_id_1="OP3" atom_id_2="P">
         <PDBx:value_order>sing</PDBx:value_order>
         <PDBx:pdbx_aromatic_flag>N</PDBx:pdbx_aromatic_flag>
         <PDBx:pdbx_stereo_config>N</PDBx:pdbx_stereo_config>
         <PDBx:pdbx_ordinal>1</PDBx:pdbx_ordinal>
      </PDBx:chem_comp_bond>
      <PDBx:chem_comp_bond comp_id="G" atom_id_1="OP3" atom_id_2="HOP3">
         <PDBx:value_order>sing</PDBx:value_order>
         <PDBx:pdbx_aromatic_flag>N</PDBx:pdbx_aromatic_flag>
         <PDBx:pdbx_stereo_config>N</PDBx:pdbx_stereo_config>
         <PDBx:pdbx_ordinal>2</PDBx:pdbx_ordinal>
      </PDBx:chem_comp_bond>
      <PDBx:chem_comp_bond comp_id="G" atom_id_1="P" atom_id_2="OP1">
         <PDBx:value_order>doub</PDBx:value_order>
         <PDBx:pdbx_aromatic_flag>N</PDBx:pdbx_aromatic_flag>
         <PDBx:pdbx_stereo_config>N</PDBx:pdbx_stereo_config>
         <PDBx:pdbx_ordinal>3</PDBx:pdbx_ordinal>
      </PDBx:chem_comp_bond>
      <PDBx:chem_comp_bond comp_id="G" atom_id_1="P" atom_id_2="OP2">
         <PDBx:value_order>sing</PDBx:value_order>
         <PDBx:pdbx_aromatic_flag>N</PDBx:pdbx_aromatic_flag>
         <PDBx:pdbx_stereo_config>N</PDBx:pdbx_stereo_config>
         <PDBx:pdbx_ordinal>4</PDBx:pdbx_ordinal>
      </PDBx:chem_comp_bond>
      <PDBx:chem_comp_bond comp_id="G" atom_id_1="P" atom_id_2="O5&apos;">
         <PDBx:value_order>sing</PDBx:value_order>
         <PDBx:pdbx_aromatic_flag>N</PDBx:pdbx_aromatic_flag>
         <PDBx:pdbx_stereo_config>N</PDBx:pdbx_stereo_config>
         <PDBx:pdbx_ordinal>5</PDBx:pdbx_ordinal>
      </PDBx:chem_comp_bond>
      <PDBx:chem_comp_bond comp_id="G" atom_id_1="OP2" atom_id_2="HOP2">
         <PDBx:value_order>sing</PDBx:value_order>
         <PDBx:pdbx_aromatic_flag>N</PDBx:pdbx_aromatic_flag>
         <PDBx:pdbx_stereo_config>N</PDBx:pdbx_stereo_config>
         <PDBx:pdbx_ordinal>6</PDBx:pdbx_ordinal>
      </PDBx:chem_comp_bond>
      <PDBx:chem_comp_bond comp_id="G" atom_id_1="O5&apos;" atom_id_2="C5&apos;">
         <PDBx:value_order>sing</PDBx:value_order>
         <PDBx:pdbx_aromatic_flag>N</PDBx:pdbx_aromatic_flag>
         <PDBx:pdbx_stereo_config>N</PDBx:pdbx_stereo_config>
         <PDBx:pdbx_ordinal>7</PDBx:pdbx_ordinal>
      </PDBx:chem_comp_bond>
      <PDBx:chem_comp_bond comp_id="G" atom_id_1="C5&apos;" atom_id_2="C4&apos;">
         <PDBx:value_order>sing</PDBx:value_order>
         <PDBx:pdbx_aromatic_flag>N</PDBx:pdbx_aromatic_flag>
         <PDBx:pdbx_stereo_config>N</PDBx:pdbx_stereo_config>
         <PDBx:pdbx_ordinal>8</PDBx:pdbx_ordinal>
      </PDBx:chem_comp_bond>
      <PDBx:chem_comp_bond comp_id="G" atom_id_1="C5&apos;" atom_id_2="H5&apos;">
         <PDBx:value_order>sing</PDBx:value_order>
         <PDBx:pdbx_aromatic_flag>N</PDBx:pdbx_aromatic_flag>
         <PDBx:pdbx_stereo_config>N</PDBx:pdbx_stereo_config>
         <PDBx:pdbx_ordinal>9</PDBx:pdbx_ordinal>
      </PDBx:chem_comp_bond>
      <PDBx:chem_comp_bond comp_id="G" atom_id_1="C5&apos;" atom_id_2="H5&apos;&apos;">
         <PDBx:value_order>sing</PDBx:value_order>
         <PDBx:pdbx_aromatic_flag>N</PDBx:pdbx_aromatic_flag>
         <PDBx:pdbx_stereo_config>N</PDBx:pdbx_stereo_config>
         <PDBx:pdbx_ordinal>10</PDBx:pdbx_ordinal>
      </PDBx:chem_comp_bond>
      <PDBx:chem_comp_bond comp_id="G" atom_id_1="C4&apos;" atom_id_2="O4&apos;">
         <PDBx:value_order>sing</PDBx:value_order>
         <PDBx:pdbx_aromatic_flag>N</PDBx:pdbx_aromatic_flag>
         <PDBx:pdbx_stereo_config>N</PDBx:pdbx_stereo_config>
         <PDBx:pdbx_ordinal>11</PDBx:pdbx_ordinal>
      </PDBx:chem_comp_bond>
      <PDBx:chem_comp_bond comp_id="G" atom_id_1="C4&apos;" atom_id_2="C3&apos;">
         <PDBx:value_order>sing</PDBx:value_order>
         <PDBx:pdbx_aromatic_flag>N</PDBx:pdbx_aromatic_flag>
         <PDBx:pdbx_stereo_config>N</PDBx:pdbx_stereo_config>
         <PDBx:pdbx_ordinal>12</PDBx:pdbx_ordinal>
      </PDBx:chem_comp_bond>
      <PDBx:chem_comp_bond comp_id="G" atom_id_1="C4&apos;" atom_id_2="H4&apos;">
         <PDBx:value_order>sing</PDBx:value_order>
         <PDBx:pdbx_aromatic_flag>N</PDBx:pdbx_aromatic_flag>
         <PDBx:pdbx_stereo_config>N</PDBx:pdbx_stereo_config>
         <PDBx:pdbx_ordinal>13</PDBx:pdbx_ordinal>
      </PDBx:chem_comp_bond>
      <PDBx:chem_comp_bond comp_id="G" atom_id_1="O4&apos;" atom_id_2="C1&apos;">
         <PDBx:value_order>sing</PDBx:value_order>
         <PDBx:pdbx_aromatic_flag>N</PDBx:pdbx_aromatic_flag>
         <PDBx:pdbx_stereo_config>N</PDBx:pdbx_stereo_config>
         <PDBx:pdbx_ordinal>14</PDBx:pdbx_ordinal>
      </PDBx:chem_comp_bond>
      <PDBx:chem_comp_bond comp_id="G" atom_id_1="C3&apos;" atom_id_2="O3&apos;">
         <PDBx:value_order>sing</PDBx:value_order>
         <PDBx:pdbx_aromatic_flag>N</PDBx:pdbx_aromatic_flag>
         <PDBx:pdbx_stereo_config>N</PDBx:pdbx_stereo_config>
         <PDBx:pdbx_ordinal>15</PDBx:pdbx_ordinal>
      </PDBx:chem_comp_bond>
      <PDBx:chem_comp_bond comp_id="G" atom_id_1="C3&apos;" atom_id_2="C2&apos;">
         <PDBx:value_order>sing</PDBx:value_order>
         <PDBx:pdbx_aromatic_flag>N</PDBx:pdbx_aromatic_flag>
         <PDBx:pdbx_stereo_config>N</PDBx:pdbx_stereo_config>
         <PDBx:pdbx_ordinal>16</PDBx:pdbx_ordinal>
      </PDBx:chem_comp_bond>
      <PDBx:chem_comp_bond comp_id="G" atom_id_1="C3&apos;" atom_id_2="H3&apos;">
         <PDBx:value_order>sing</PDBx:value_order>
         <PDBx:pdbx_aromatic_flag>N</PDBx:pdbx_aromatic_flag>
         <PDBx:pdbx_stereo_config>N</PDBx:pdbx_stereo_config>
         <PDBx:pdbx_ordinal>17</PDBx:pdbx_ordinal>
      </PDBx:chem_comp_bond>
      <PDBx:chem_comp_bond comp_id="G" atom_id_1="O3&apos;" atom_id_2="HO3&apos;">
         <PDBx:value_order>sing</PDBx:value_order>
         <PDBx:pdbx_aromatic_flag>N</PDBx:pdbx_aromatic_flag>
         <PDBx:pdbx_stereo_config>N</PDBx:pdbx_stereo_config>
         <PDBx:pdbx_ordinal>18</PDBx:pdbx_ordinal>
      </PDBx:chem_comp_bond>
      <PDBx:chem_comp_bond comp_id="G" atom_id_1="C2&apos;" atom_id_2="O2&apos;">
         <PDBx:value_order>sing</PDBx:value_order>
         <PDBx:pdbx_aromatic_flag>N</PDBx:pdbx_aromatic_flag>
         <PDBx:pdbx_stereo_config>N</PDBx:pdbx_stereo_config>
         <PDBx:pdbx_ordinal>19</PDBx:pdbx_ordinal>
      </PDBx:chem_comp_bond>
      <PDBx:chem_comp_bond comp_id="G" atom_id_1="C2&apos;" atom_id_2="C1&apos;">
         <PDBx:value_order>sing</PDBx:value_order>
         <PDBx:pdbx_aromatic_flag>N</PDBx:pdbx_aromatic_flag>
         <PDBx:pdbx_stereo_config>N</PDBx:pdbx_stereo_config>
         <PDBx:pdbx_ordinal>20</PDBx:pdbx_ordinal>
      </PDBx:chem_comp_bond>
      <PDBx:chem_comp_bond comp_id="G" atom_id_1="C2&apos;" atom_id_2="H2&apos;">
         <PDBx:value_order>sing</PDBx:value_order>
         <PDBx:pdbx_aromatic_flag>N</PDBx:pdbx_aromatic_flag>
         <PDBx:pdbx_stereo_config>N</PDBx:pdbx_stereo_config>
         <PDBx:pdbx_ordinal>21</PDBx:pdbx_ordinal>
      </PDBx:chem_comp_bond>
      <PDBx:chem_comp_bond comp_id="G" atom_id_1="O2&apos;" atom_id_2="HO2&apos;">
         <PDBx:value_order>sing</PDBx:value_order>
         <PDBx:pdbx_aromatic_flag>N</PDBx:pdbx_aromatic_flag>
         <PDBx:pdbx_stereo_config>N</PDBx:pdbx_stereo_config>
         <PDBx:pdbx_ordinal>22</PDBx:pdbx_ordinal>
      </PDBx:chem_comp_bond>
      <PDBx:chem_comp_bond comp_id="G" atom_id_1="C1&apos;" atom_id_2="N9">
         <PDBx:value_order>sing</PDBx:value_order>
         <PDBx:pdbx_aromatic_flag>N</PDBx:pdbx_aromatic_flag>
         <PDBx:pdbx_stereo_config>N</PDBx:pdbx_stereo_config>
         <PDBx:pdbx_ordinal>23</PDBx:pdbx_ordinal>
      </PDBx:chem_comp_bond>
      <PDBx:chem_comp_bond comp_id="G" atom_id_1="C1&apos;" atom_id_2="H1&apos;">
         <PDBx:value_order>sing</PDBx:value_order>
         <PDBx:pdbx_aromatic_flag>N</PDBx:pdbx_aromatic_flag>
         <PDBx:pdbx_stereo_config>N</PDBx:pdbx_stereo_config>
         <PDBx:pdbx_ordinal>24</PDBx:pdbx_ordinal>
      </PDBx:chem_comp_bond>
      <PDBx:chem_comp_bond comp_id="G" atom_id_1="N9" atom_id_2="C8">
         <PDBx:value_order>sing</PDBx:value_order>
         <PDBx:pdbx_aromatic_flag>Y</PDBx:pdbx_aromatic_flag>
         <PDBx:pdbx_stereo_config>N</PDBx:pdbx_stereo_config>
         <PDBx:pdbx_ordinal>25</PDBx:pdbx_ordinal>
      </PDBx:chem_comp_bond>
      <PDBx:chem_comp_bond comp_id="G" atom_id_1="N9" atom_id_2="C4">
         <PDBx:value_order>sing</PDBx:value_order>
         <PDBx:pdbx_aromatic_flag>Y</PDBx:pdbx_aromatic_flag>
         <PDBx:pdbx_stereo_config>N</PDBx:pdbx_stereo_config>
         <PDBx:pdbx_ordinal>26</PDBx:pdbx_ordinal>
      </PDBx:chem_comp_bond>
      <PDBx:chem_comp_bond comp_id="G" atom_id_1="C8" atom_id_2="N7">
         <PDBx:value_order>doub</PDBx:value_order>
         <PDBx:pdbx_aromatic_flag>Y</PDBx:pdbx_aromatic_flag>
         <PDBx:pdbx_stereo_config>N</PDBx:pdbx_stereo_config>
         <PDBx:pdbx_ordinal>27</PDBx:pdbx_ordinal>
      </PDBx:chem_comp_bond>
      <PDBx:chem_comp_bond comp_id="G" atom_id_1="C8" atom_id_2="H8">
         <PDBx:value_order>sing</PDBx:value_order>
         <PDBx:pdbx_aromatic_flag>N</PDBx:pdbx_aromatic_flag>
         <PDBx:pdbx_stereo_config>N</PDBx:pdbx_stereo_config>
         <PDBx:pdbx_ordinal>28</PDBx:pdbx_ordinal>
      </PDBx:chem_comp_bond>
      <PDBx:chem_comp_bond comp_id="G" atom_id_1="N7" atom_id_2="C5">
         <PDBx:value_order>sing</PDBx:value_order>
         <PDBx:pdbx_aromatic_flag>Y</PDBx:pdbx_aromatic_flag>
         <PDBx:pdbx_stereo_config>N</PDBx:pdbx_stereo_config>
         <PDBx:pdbx_ordinal>29</PDBx:pdbx_ordinal>
      </PDBx:chem_comp_bond>
      <PDBx:chem_comp_bond comp_id="G" atom_id_1="C5" atom_id_2="C6">
         <PDBx:value_order>sing</PDBx:value_order>
         <PDBx:pdbx_aromatic_flag>N</PDBx:pdbx_aromatic_flag>
         <PDBx:pdbx_stereo_config>N</PDBx:pdbx_stereo_config>
         <PDBx:pdbx_ordinal>30</PDBx:pdbx_ordinal>
      </PDBx:chem_comp_bond>
      <PDBx:chem_comp_bond comp_id="G" atom_id_1="C5" atom_id_2="C4">
         <PDBx:value_order>doub</PDBx:value_order>
         <PDBx:pdbx_aromatic_flag>Y</PDBx:pdbx_aromatic_flag>
         <PDBx:pdbx_stereo_config>N</PDBx:pdbx_stereo_config>
         <PDBx:pdbx_ordinal>31</PDBx:pdbx_ordinal>
      </PDBx:chem_comp_bond>
      <PDBx:chem_comp_bond comp_id="G" atom_id_1="C6" atom_id_2="O6">
         <PDBx:value_order>doub</PDBx:value_order>
         <PDBx:pdbx_aromatic_flag>N</PDBx:pdbx_aromatic_flag>
         <PDBx:pdbx_stereo_config>N</PDBx:pdbx_stereo_config>
         <PDBx:pdbx_ordinal>32</PDBx:pdbx_ordinal>
      </PDBx:chem_comp_bond>
      <PDBx:chem_comp_bond comp_id="G" atom_id_1="C6" atom_id_2="N1">
         <PDBx:value_order>sing</PDBx:value_order>
         <PDBx:pdbx_aromatic_flag>N</PDBx:pdbx_aromatic_flag>
         <PDBx:pdbx_stereo_config>N</PDBx:pdbx_stereo_config>
         <PDBx:pdbx_ordinal>33</PDBx:pdbx_ordinal>
      </PDBx:chem_comp_bond>
      <PDBx:chem_comp_bond comp_id="G" atom_id_1="N1" atom_id_2="C2">
         <PDBx:value_order>sing</PDBx:value_order>
         <PDBx:pdbx_aromatic_flag>N</PDBx:pdbx_aromatic_flag>
         <PDBx:pdbx_stereo_config>N</PDBx:pdbx_stereo_config>
         <PDBx:pdbx_ordinal>34</PDBx:pdbx_ordinal>
      </PDBx:chem_comp_bond>
      <PDBx:chem_comp_bond comp_id="G" atom_id_1="N1" atom_id_2="H1">
         <PDBx:value_order>sing</PDBx:value_order>
         <PDBx:pdbx_aromatic_flag>N</PDBx:pdbx_aromatic_flag>
         <PDBx:pdbx_stereo_config>N</PDBx:pdbx_stereo_config>
         <PDBx:pdbx_ordinal>35</PDBx:pdbx_ordinal>
      </PDBx:chem_comp_bond>
      <PDBx:chem_comp_bond comp_id="G" atom_id_1="C2" atom_id_2="N2">
         <PDBx:value_order>sing</PDBx:value_order>
         <PDBx:pdbx_aromatic_flag>N</PDBx:pdbx_aromatic_flag>
         <PDBx:pdbx_stereo_config>N</PDBx:pdbx_stereo_config>
         <PDBx:pdbx_ordinal>36</PDBx:pdbx_ordinal>
      </PDBx:chem_comp_bond>
      <PDBx:chem_comp_bond comp_id="G" atom_id_1="C2" atom_id_2="N3">
         <PDBx:value_order>doub</PDBx:value_order>
         <PDBx:pdbx_aromatic_flag>N</PDBx:pdbx_aromatic_flag>
         <PDBx:pdbx_stereo_config>N</PDBx:pdbx_stereo_config>
         <PDBx:pdbx_ordinal>37</PDBx:pdbx_ordinal>
      </PDBx:chem_comp_bond>
      <PDBx:chem_comp_bond comp_id="G" atom_id_1="N2" atom_id_2="H21">
         <PDBx:value_order>sing</PDBx:value_order>
         <PDBx:pdbx_aromatic_flag>N</PDBx:pdbx_aromatic_flag>
         <PDBx:pdbx_stereo_config>N</PDBx:pdbx_stereo_config>
         <PDBx:pdbx_ordinal>38</PDBx:pdbx_ordinal>
      </PDBx:chem_comp_bond>
      <PDBx:chem_comp_bond comp_id="G" atom_id_1="N2" atom_id_2="H22">
         <PDBx:value_order>sing</PDBx:value_order>
         <PDBx:pdbx_aromatic_flag>N</PDBx:pdbx_aromatic_flag>
         <PDBx:pdbx_stereo_config>N</PDBx:pdbx_stereo_config>
         <PDBx:pdbx_ordinal>39</PDBx:pdbx_ordinal>
      </PDBx:chem_comp_bond>
      <PDBx:chem_comp_bond comp_id="G" atom_id_1="N3" atom_id_2="C4">
         <PDBx:value_order>sing</PDBx:value_order>
         <PDBx:pdbx_aromatic_flag>N</PDBx:pdbx_aromatic_flag>
         <PDBx:pdbx_stereo_config>N</PDBx:pdbx_stereo_config>
         <PDBx:pdbx_ordinal>40</PDBx:pdbx_ordinal>
      </PDBx:chem_comp_bond>
   </PDBx:chem_comp_bondCategory>
   <PDBx:pdbx_chem_comp_descriptorCategory>
      <PDBx:pdbx_chem_comp_descriptor comp_id="G" type="SMILES" program="ACDLabs" program_version="10.04">
         <PDBx:descriptor>O=C1c2ncn(c2N=C(N)N1)C3OC(C(O)C3O)COP(=O)(O)O</PDBx:descriptor>
      </PDBx:pdbx_chem_comp_descriptor>
      <PDBx:pdbx_chem_comp_descriptor comp_id="G" type="SMILES_CANONICAL" program="CACTVS" program_version="3.341">
         <PDBx:descriptor>NC1=Nc2n(cnc2C(=O)N1)[C@@H]3O[C@H](CO[P](O)(O)=O)[C@@H](O)[C@H]3O</PDBx:descriptor>
      </PDBx:pdbx_chem_comp_descriptor>
      <PDBx:pdbx_chem_comp_descriptor comp_id="G" type="SMILES" program="CACTVS" program_version="3.341">
         <PDBx:descriptor>NC1=Nc2n(cnc2C(=O)N1)[CH]3O[CH](CO[P](O)(O)=O)[CH](O)[CH]3O</PDBx:descriptor>
      </PDBx:pdbx_chem_comp_descriptor>
      <PDBx:pdbx_chem_comp_descriptor comp_id="G" type="SMILES_CANONICAL" program="OpenEye OEToolkits" program_version="1.5.0">
         <PDBx:descriptor>c1nc2c(n1[C@H]3[C@@H]([C@@H]([C@H](O3)COP(=O)(O)O)O)O)N=C(NC2=O)N</PDBx:descriptor>
      </PDBx:pdbx_chem_comp_descriptor>
      <PDBx:pdbx_chem_comp_descriptor comp_id="G" type="SMILES" program="OpenEye OEToolkits" program_version="1.5.0">
         <PDBx:descriptor>c1nc2c(n1C3C(C(C(O3)COP(=O)(O)O)O)O)N=C(NC2=O)N</PDBx:descriptor>
      </PDBx:pdbx_chem_comp_descriptor>
      <PDBx:pdbx_chem_comp_descriptor comp_id="G" type="InChI" program="InChI" program_version="1.03">
         <PDBx:descriptor>InChI=1S/C10H14N5O8P/c11-10-13-7-4(8(18)14-10)12-2-15(7)9-6(17)5(16)3(23-9)1-22-24(19,20)21/h2-3,5-6,9,16-17H,1H2,(H2,19,20,21)(H3,11,13,14,18)/t3-,5-,6-,9-/m1/s1</PDBx:descriptor>
      </PDBx:pdbx_chem_comp_descriptor>
      <PDBx:pdbx_chem_comp_descriptor comp_id="G" type="InChIKey" program="InChI" program_version="1.03">
         <PDBx:descriptor>RQFCJASXJCIDSX-UUOKFMHZSA-N</PDBx:descriptor>
      </PDBx:pdbx_chem_comp_descriptor>
   </PDBx:pdbx_chem_comp_descriptorCategory>
   <PDBx:pdbx_chem_comp_identifierCategory>
      <PDBx:pdbx_chem_comp_identifier comp_id="G" type="SYSTEMATIC NAME" program="ACDLabs" program_version="10.04">
         <PDBx:identifier>5&apos;-guanylic acid</PDBx:identifier>
      </PDBx:pdbx_chem_comp_identifier>
      <PDBx:pdbx_chem_comp_identifier comp_id="G" type="SYSTEMATIC NAME" program="OpenEye OEToolkits" program_version="1.5.0">
         <PDBx:identifier>[(2R,3S,4R,5R)-5-(2-amino-6-oxo-1H-purin-9-yl)-3,4-dihydroxy-oxolan-2-yl]methyl dihydrogen phosphate</PDBx:identifier>
      </PDBx:pdbx_chem_comp_identifier>
   </PDBx:pdbx_chem_comp_identifierCategory>
   <PDBx:pdbx_chem_comp_auditCategory>
      <PDBx:pdbx_chem_comp_audit comp_id="G" action_type="Create component" date="1999-07-08">
         <PDBx:processing_site>RCSB</PDBx:processing_site>
      </PDBx:pdbx_chem_comp_audit>
      <PDBx:pdbx_chem_comp_audit comp_id="G" action_type="Modify descriptor" date="2011-06-04">
         <PDBx:processing_site>RCSB</PDBx:processing_site>
      </PDBx:pdbx_chem_comp_audit>
   </PDBx:pdbx_chem_comp_auditCategory>
</PDBx:datablock>
